loops_sdk.py
loops_sdk-0.3.2.dist-info/licenses/LICENSE
loops_sdk-0.3.2.dist-info/METADATA
loops_sdk-0.3.2.dist-info/WHEEL
loops_sdk-0.3.2.dist-info/top_level.txt
loops_sdk-0.3.2.dist-info/RECORD
