Metadata-Version: 2.4
Name: loops-sdk
Version: 0.3.2
Summary: Loops SDK for Python
Author-email: Adrian Chen <pypi@familiar.pub>
License: MIT
Project-URL: Homepage, https://github.com/infernal-moose/loops-python
Project-URL: Issues, https://github.com/infernal-moose/loops-python/issues
Requires-Python: >=3.9
License-File: LICENSE
Requires-Dist: requests<3.0.0,>=2.31.0
Provides-Extra: test
Requires-Dist: pytest<8.0.0,>=7.4.4; extra == "test"
Requires-Dist: pytest-mock<4.0.0,>=3.14.0; extra == "test"
Requires-Dist: coverage<8.0.0,>=7.4.4; extra == "test"
Requires-Dist: ruff<0.5.0,>=0.4.4; extra == "test"
Requires-Dist: pre-commit<5.0.0,>=4.2.0; extra == "test"
Requires-Dist: build<2.0.0,>=1.2.2.post1; extra == "test"
Requires-Dist: twine<7.0.0,>=6.1.0; extra == "test"
Dynamic: license-file
